imgaugmentation/ImageAugmentation.py
imgaugmentation/__init__.py
imgaugmentation-0.0a0.dist-info/LICENSE
imgaugmentation-0.0a0.dist-info/METADATA
imgaugmentation-0.0a0.dist-info/WHEEL
imgaugmentation-0.0a0.dist-info/top_level.txt
imgaugmentation-0.0a0.dist-info/RECORD
