Metadata-Version: 2.1
Name: imgaugmentation
Version: 0.0a0
Summary: This package is for Data augmentation of image dataset
Home-page: UNKNOWN
Author: Sumit Singh
Author-email: <iamsumit1904@gmail.com>
License: UNKNOWN
Keywords: python,augmentation,image,data augmentation,image dataset
Platform: UNKNOWN
Classifier: Development Status :: 1 - Planning
Classifier: Intended Audience :: Developers
Classifier: Programming Language :: Python :: 3
Classifier: Operating System :: Unix
Classifier: Operating System :: MacOS :: MacOS X
Classifier: Operating System :: Microsoft :: Windows
Requires-Dist: opencv-python
Requires-Dist: numpy
Requires-Dist: matplotlib
